routely/__init__.py
routely/routely.py
routely-0.1.4.dist-info/LICENSE
routely-0.1.4.dist-info/METADATA
routely-0.1.4.dist-info/WHEEL
routely-0.1.4.dist-info/top_level.txt
routely-0.1.4.dist-info/RECORD
