Metadata-Version: 2.1
Name: routely
Version: 0.1.4
Summary: Common operations and transformations on routes represented by a 2D line in xy space and corresponding z-axis data.
Home-page: https://github.com/jhags/routely
Author: J Hagstrom
License: MIT
Platform: UNKNOWN
Classifier: License :: OSI Approved :: MIT License
Classifier: Programming Language :: Python :: 3
Classifier: Programming Language :: Python :: 3.7
Requires-Python: >=3.7
Requires-Dist: numpy (>=1.20)
Requires-Dist: scipy
Requires-Dist: matplotlib
Requires-Dist: pandas
